hub_datatools/console.py
hub_datatools/serialize.py
hub_datatools/transform.py
hub_datatools-1.4.1.dist-info/LICENSE
hub_datatools-1.4.1.dist-info/METADATA
hub_datatools-1.4.1.dist-info/WHEEL
hub_datatools-1.4.1.dist-info/entry_points.txt
hub_datatools-1.4.1.dist-info/top_level.txt
hub_datatools-1.4.1.dist-info/RECORD
